keel_telegram_bot/__init__.py
keel_telegram_bot/api_client.py
keel_telegram_bot/config.py
keel_telegram_bot/const.py
keel_telegram_bot/main.py
keel_telegram_bot/stats.py
keel_telegram_bot/util.py
keel_telegram_bot/webserver.py
keel_telegram_bot/bot/__init__.py
keel_telegram_bot/bot/permissions.py
keel_telegram_bot/bot/reply_keyboard_handler.py
keel_telegram_bot/monitoring/__init__.py
keel_telegram_bot/monitoring/monitor.py
tests/__init__.py
tests/test_bot.py
tests/test_dummy.py
keel_telegram_bot-1.3.1.dist-info/LICENSE
keel_telegram_bot-1.3.1.dist-info/METADATA
keel_telegram_bot-1.3.1.dist-info/WHEEL
keel_telegram_bot-1.3.1.dist-info/entry_points.txt
keel_telegram_bot-1.3.1.dist-info/top_level.txt
keel_telegram_bot-1.3.1.dist-info/RECORD
