Metadata-Version: 2.1
Name: keel-telegram-bot
Version: 1.3.1
Summary: A telegram bot for keel.sh
Home-page: https://github.com/markusressel/keel-telegram-bot
Author: Markus Ressel
Author-email: mail@markusressel.de
License: AGPLv3+
Classifier: Development Status :: 5 - Production/Stable
Classifier: License :: OSI Approved :: GNU General Public License v3 or later (GPLv3+)
Classifier: Programming Language :: Python :: 3
Classifier: Programming Language :: Python :: 3.8
License-File: LICENSE
Requires-Dist: aiohttp (==3.8.3)
Requires-Dist: aiosignal (==1.3.1)
Requires-Dist: anyio (==3.6.2)
Requires-Dist: asgiref (==3.6.0)
Requires-Dist: async-timeout (==4.0.2)
Requires-Dist: attrs (==22.2.0)
Requires-Dist: certifi (==2022.12.7)
Requires-Dist: charset-normalizer (==2.1.1)
Requires-Dist: click (==8.1.3)
Requires-Dist: container-app-conf (==5.2.2)
Requires-Dist: emoji (==2.2.0)
Requires-Dist: flask (==2.2.2)
Requires-Dist: frozenlist (==1.3.3)
Requires-Dist: fuzzywuzzy (==0.18.0)
Requires-Dist: h11 (==0.14.0)
Requires-Dist: h2 (==4.1.0)
Requires-Dist: hpack (==4.0.0)
Requires-Dist: httpcore (==0.16.3)
Requires-Dist: httpx (==0.23.3)
Requires-Dist: hyperframe (==6.0.1)
Requires-Dist: idna (==3.4)
Requires-Dist: iso8601 (==1.1.0)
Requires-Dist: itsdangerous (==2.1.2)
Requires-Dist: jinja2 (==3.1.2)
Requires-Dist: levenshtein (==0.20.9)
Requires-Dist: markupsafe (==2.1.2)
Requires-Dist: multidict (==6.0.4)
Requires-Dist: prometheus-async (==22.2.0)
Requires-Dist: prometheus-client (==0.16.0)
Requires-Dist: py-range-parse (==1.0.5)
Requires-Dist: python-dateutil (==2.8.2)
Requires-Dist: python-levenshtein (==0.20.9)
Requires-Dist: python-telegram-bot (==20.1)
Requires-Dist: pytimeparse (==1.1.8)
Requires-Dist: rapidfuzz (==2.13.7)
Requires-Dist: requests (==2.28.2)
Requires-Dist: rfc3986 (==1.5.0)
Requires-Dist: ruamel.yaml (==0.17.21)
Requires-Dist: ruamel.yaml.clib (==0.2.7)
Requires-Dist: six (==1.16.0)
Requires-Dist: sniffio (==1.3.0)
Requires-Dist: telegram-click (==6.0.2)
Requires-Dist: toml (==0.10.2)
Requires-Dist: urllib3 (==1.26.14)
Requires-Dist: voluptuous (==0.13.1)
Requires-Dist: werkzeug (==2.2.2)
Requires-Dist: wrapt (==1.14.1)
Requires-Dist: yarl (==1.8.2)
